{
  "id": "blog-posts-20260416095747-мои-твиты",
  "source_url": "https://platerra.livejournal.com/22784.html",
  "timestamp": "20260416095747",
  "title": "Мои твиты",
  "category": "blog-posts",
  "content_hash": "a8fb0e6823e98ba2a2cd439fd25b2484281f22144dd6a9c4c6f9927a9e1af96f",
  "text_path": "recovered_lj/blog-posts/blog-posts-20260416095747-мои-твиты/text.md",
  "metadata_path": "recovered_lj/blog-posts/blog-posts-20260416095747-мои-твиты/metadata.json",
  "images": [],
  "notes": {
    "source": "Direct scrape from platerra.livejournal.com"
  }
}