{
  "id": "blog-posts-20260416093405-мои-твиты",
  "source_url": "https://platerra.livejournal.com/15104.html",
  "timestamp": "20260416093405",
  "title": "Мои твиты",
  "category": "blog-posts",
  "content_hash": "1ebc1b0462725b8df882a3138575114567c741d6fccf9bae5ef472fec37bc269",
  "text_path": "recovered_lj/blog-posts/blog-posts-20260416093405-мои-твиты/text.md",
  "metadata_path": "recovered_lj/blog-posts/blog-posts-20260416093405-мои-твиты/metadata.json",
  "images": [],
  "notes": {
    "source": "Direct scrape from platerra.livejournal.com"
  }
}