{
  "id": "blog-posts-20260416092024-платежная-система-обновленный-интерфейс-для-госплатежей",
  "source_url": "https://platerra.livejournal.com/10752.html",
  "timestamp": "20260416092024",
  "title": "Платежная система. Обновленный интерфейс для госплатежей",
  "category": "blog-posts",
  "content_hash": "bb6f5f4c6e910185a5c82a36e9faa486abd035c621ac14ffb7365cfd6e8bcda9",
  "text_path": "recovered_lj/blog-posts/blog-posts-20260416092024-платежная-система-обновленный-интерфейс-для-госплатежей/text.md",
  "metadata_path": "recovered_lj/blog-posts/blog-posts-20260416092024-платежная-система-обновленный-интерфейс-для-госплатежей/metadata.json",
  "images": [],
  "notes": {
    "source": "Direct scrape from platerra.livejournal.com"
  }
}